music_finder_micro/__init__.py
music_finder_micro/_artist.py
music_finder_micro/_database.py
music_finder_micro/_finder_result.py
music_finder_micro/music_finder.py
music_finder_micro-0.1.2.dist-info/METADATA
music_finder_micro-0.1.2.dist-info/WHEEL
music_finder_micro-0.1.2.dist-info/licenses/LICENSE
music_finder_micro-0.1.2.dist-info/RECORD
